db_autotest/__init__.py
db_autotest/lite_object/__init__.py
db_autotest/lite_object/c_m_table.py
db_autotest/lite_object/c_m_table_names.py
db_autotest/load_mssql_meta/__init__.py
db_autotest/load_mssql_meta/mss_load_inserts.py
db_autotest/load_mssql_meta/mss_load_version_indexes.py
db_autotest/load_mssql_meta/mss_load_version_tables.py
db_autotest/load_sqlite_meta/__init__.py
db_autotest/load_sqlite_meta/load.py
db_autotest/load_sqlite_meta/load_columns.py
db_autotest/load_sqlite_meta/load_indexes.py
db_autotest/load_sqlite_meta/load_tables.py
db_autotest/load_sqlite_meta/load_version.py
db_autotest/load_sqlite_meta/load_version_idx_cols.py
db_autotest/load_sqlite_meta/load_version_indexes.py
db_autotest/load_sqlite_meta/load_version_tab_cols.py
db_autotest/load_sqlite_meta/load_version_tables.py
db_autotest/m_lib/__init__.py
db_autotest/m_lib/m_config/__del__.py
db_autotest/m_lib/m_config/__init__.py
db_autotest/m_lib/m_config/config.py
db_autotest/m_lib/m_object/__init__.py
db_autotest/m_lib/m_object/m_class.py
db_autotest/m_lib/m_object/m_entity.py
db_autotest/m_lib/m_object/m_relation.py
db_autotest/m_lib/m_object/m_str_type_enum.py
db_autotest/m_lib/m_object/m_structure.py
db_autotest/m_lib/m_table/__init__.py
db_autotest/m_lib/m_table/m_row.py
db_autotest/m_lib/m_table/m_table.py
db_autotest/m_lib/m_utils/connect_db.py
db_autotest/m_lib/m_utils/generate_tab_cols.py
db_autotest/m_lib/m_utils/m_entity_selects.py
db_autotest/m_lib/m_utils/m_entity_utils.py
db_autotest/m_lib/m_utils/m_yaml.py
db_autotest/m_lib/m_utils/selects.py
db_autotest/scripts/__init__.py
db_autotest/scripts/script_code.py
db_autotest/scripts/script_db.py
db_autotest-0.0.6.dist-info/METADATA
db_autotest-0.0.6.dist-info/WHEEL
db_autotest-0.0.6.dist-info/licenses/LICENSE
db_autotest-0.0.6.dist-info/RECORD
