Metadata-Version: 2.1
Name: db-autotest
Version: 0.0.6
Summary: DB Database test automation. This package allows to create database object structure and load data from database.
Project-URL: Homepage, https://github.com/AcaciaMan/db-autotest
Project-URL: Issues, https://github.com/AcaciaMan/db-autotest/issues
Author-email: AcaciaMan <11488694+AcaciaMan@users.noreply.github.com>
License-File: LICENSE
Classifier: License :: OSI Approved :: Apache Software License
Classifier: Operating System :: OS Independent
Classifier: Programming Language :: Python :: 3
Requires-Python: >=3.12
Requires-Dist: pyyaml>=6
